serdelicacy/__init__.py
serdelicacy/deserialize.py
serdelicacy/errors.py
serdelicacy/overrides.py
serdelicacy/py.typed
serdelicacy/serialize.py
serdelicacy/typedefs.py
serdelicacy-0.18.1.dist-info/LICENSE
serdelicacy-0.18.1.dist-info/WHEEL
serdelicacy-0.18.1.dist-info/METADATA
serdelicacy-0.18.1.dist-info/RECORD
