Metadata-Version: 2.1
Name: serdelicacy
Version: 0.18.1
Summary: Serialize/deserialize Python objects from/to typed structures.
Home-page: https://github.com/pappasam/serdelicacy
License: MIT
Keywords: typing,dataclass,namedtuple,json,serde,serialize,deserialize
Author: Sam Roeca
Author-email: samuel.roeca@gmail.com
Requires-Python: >=3.8,<4.0
Classifier: Development Status :: 3 - Alpha
Classifier: License :: OSI Approved :: MIT License
Classifier: Operating System :: OS Independent
Classifier: Programming Language :: Python :: 3
Classifier: Programming Language :: Python :: 3.8
Classifier: Programming Language :: Python :: 3.9
Classifier: Topic :: Software Development :: Libraries :: Python Modules
Classifier: Topic :: Utilities
Classifier: Typing :: Typed
Provides-Extra: docs
Requires-Dist: Sphinx (>=3.3.1,<4.0.0); extra == "docs"
Requires-Dist: m2r2 (>=0.2.7,<0.3.0); extra == "docs"
Requires-Dist: sphinx-rtd-theme (>=0.5.0,<0.6.0); extra == "docs"
Requires-Dist: toml (>=0.10.2,<0.11.0); extra == "docs"
Project-URL: Repository, https://github.com/pappasam/serdelicacy
